pysdif3-1.0.1.data/scripts/sdifinfo
pysdif3-1.0.1.dist-info/RECORD
pysdif3-1.0.1.dist-info/WHEEL
pysdif3-1.0.1.dist-info/top_level.txt
pysdif3-1.0.1.dist-info/LICENSE.txt
pysdif3-1.0.1.dist-info/METADATA
pysdif/version.py
pysdif/tools.py
pysdif/__init__.py
pysdif/bench.py
pysdif/_pysdif.cpython-310-darwin.so
pysdif/markers.py
pysdif/_pysdif.c
pysdif/data/SdifTypes.STYP
